{"has_projects":true,"blobs_url":"https:\/\/api.github.com\/repos\/4d-for-ios\/formatter-IntegerToImage\/git\/blobs{\/sha}","subscription_url":"https:\/\/api.github.com\/repos\/4d-for-ios\/formatter-IntegerToImage\/subscription","compare_url":"https:\/\/api.github.com\/repos\/4d-for-ios\/formatter-IntegerToImage\/compare\/{base}...{head}","clone_url":"https:\/\/github.com\/4d-for-ios\/formatter-IntegerToImage.git","organization":{"url":"https:\/\/api.github.com\/users\/4d-for-ios","avatar_url":"https:\/\/avatars.githubusercontent.com\/u\/57483781?v=4","login":"4d-for-ios","site_admin":false,"type":"Organization","id":57483781,"node_id":"MDEyOk9yZ2FuaXphdGlvbjU3NDgzNzgx","following_url":"https:\/\/api.github.com\/users\/4d-for-ios\/following{\/other_user}","followers_url":"https:\/\/api.github.com\/users\/4d-for-ios\/followers","subscriptions_url":"https:\/\/api.github.com\/users\/4d-for-ios\/subscriptions","starred_url":"https:\/\/api.github.com\/users\/4d-for-ios\/starred{\/owner}{\/repo}","html_url":"https:\/\/github.com\/4d-for-ios","received_events_url":"https:\/\/api.github.com\/users\/4d-for-ios\/received_events","gists_url":"https:\/\/api.github.com\/users\/4d-for-ios\/gists{\/gist_id}","repos_url":"https:\/\/api.github.com\/users\/4d-for-ios\/repos","events_url":"https:\/\/api.github.com\/users\/4d-for-ios\/events{\/privacy}","gravatar_id":"","organizations_url":"https:\/\/api.github.com\/users\/4d-for-ios\/orgs"},"license":{"spdx_id":"NOASSERTION","url":null,"key":"other","name":"Other","node_id":"MDc6TGljZW5zZTA="},"name":"formatter-IntegerToImage","teams_url":"https:\/\/api.github.com\/repos\/4d-for-ios\/formatter-IntegerToImage\/teams","disabled":false,"forks_count":0,"description":"4D for iOS Data Formatter","merges_url":"https:\/\/api.github.com\/repos\/4d-for-ios\/formatter-IntegerToImage\/merges","watchers":0,"private":false,"git_tags_url":"https:\/\/api.github.com\/repos\/4d-for-ios\/formatter-IntegerToImage\/git\/tags{\/sha}","svn_url":"https:\/\/github.com\/4d-for-ios\/formatter-IntegerToImage","watchers_count":0,"languages_url":"https:\/\/api.github.com\/repos\/4d-for-ios\/formatter-IntegerToImage\/languages","forks":0,"open_issues":0,"created_at":"2019-06-05T12:29:02Z","open_issues_count":0,"git_url":"git:\/\/github.com\/4d-for-ios\/formatter-IntegerToImage.git","keys_url":"https:\/\/api.github.com\/repos\/4d-for-ios\/formatter-IntegerToImage\/keys{\/key_id}","has_wiki":true,"issue_comment_url":"https:\/\/api.github.com\/repos\/4d-for-ios\/formatter-IntegerToImage\/issues\/comments{\/number}","pulls_url":"https:\/\/api.github.com\/repos\/4d-for-ios\/formatter-IntegerToImage\/pulls{\/number}","html_url":"https:\/\/github.com\/4d-for-ios\/formatter-IntegerToImage","hooks_url":"https:\/\/api.github.com\/repos\/4d-for-ios\/formatter-IntegerToImage\/hooks","network_count":0,"labels_url":"https:\/\/api.github.com\/repos\/4d-for-ios\/formatter-IntegerToImage\/labels{\/name}","updated_at":"2019-11-28T13:53:53Z","full_name":"4d-for-ios\/formatter-IntegerToImage","has_pages":false,"git_refs_url":"https:\/\/api.github.com\/repos\/4d-for-ios\/formatter-IntegerToImage\/git\/refs{\/sha}","pushed_at":"2019-11-28T13:53:51Z","mirror_url":null,"issue_events_url":"https:\/\/api.github.com\/repos\/4d-for-ios\/formatter-IntegerToImage\/issues\/events{\/number}","contributors_url":"https:\/\/api.github.com\/repos\/4d-for-ios\/formatter-IntegerToImage\/contributors","node_id":"MDEwOlJlcG9zaXRvcnkxOTAzOTA0NTg=","comments_url":"https:\/\/api.github.com\/repos\/4d-for-ios\/formatter-IntegerToImage\/comments{\/number}","has_downloads":true,"owner":{"url":"https:\/\/api.github.com\/users\/4d-for-ios","avatar_url":"https:\/\/avatars.githubusercontent.com\/u\/57483781?v=4","login":"4d-for-ios","site_admin":false,"type":"Organization","id":57483781,"node_id":"MDEyOk9yZ2FuaXphdGlvbjU3NDgzNzgx","following_url":"https:\/\/api.github.com\/users\/4d-for-ios\/following{\/other_user}","followers_url":"https:\/\/api.github.com\/users\/4d-for-ios\/followers","subscriptions_url":"https:\/\/api.github.com\/users\/4d-for-ios\/subscriptions","starred_url":"https:\/\/api.github.com\/users\/4d-for-ios\/starred{\/owner}{\/repo}","html_url":"https:\/\/github.com\/4d-for-ios","received_events_url":"https:\/\/api.github.com\/users\/4d-for-ios\/received_events","gists_url":"https:\/\/api.github.com\/users\/4d-for-ios\/gists{\/gist_id}","repos_url":"https:\/\/api.github.com\/users\/4d-for-ios\/repos","events_url":"https:\/\/api.github.com\/users\/4d-for-ios\/events{\/privacy}","gravatar_id":"","organizations_url":"https:\/\/api.github.com\/users\/4d-for-ios\/orgs"},"language":null,"commits_url":"https:\/\/api.github.com\/repos\/4d-for-ios\/formatter-IntegerToImage\/commits{\/sha}","id":190390458,"subscribers_count":1,"events_url":"https:\/\/api.github.com\/repos\/4d-for-ios\/formatter-IntegerToImage\/events","releases_url":"https:\/\/api.github.com\/repos\/4d-for-ios\/formatter-IntegerToImage\/releases{\/id}","downloads_url":"https:\/\/api.github.com\/repos\/4d-for-ios\/formatter-IntegerToImage\/downloads","subscribers_url":"https:\/\/api.github.com\/repos\/4d-for-ios\/formatter-IntegerToImage\/subscribers","statuses_url":"https:\/\/api.github.com\/repos\/4d-for-ios\/formatter-IntegerToImage\/statuses\/{sha}","archived":false,"permissions":{"pull":false,"push":false,"admin":false},"contents_url":"https:\/\/api.github.com\/repos\/4d-for-ios\/formatter-IntegerToImage\/contents\/{+path}","collaborators_url":"https:\/\/api.github.com\/repos\/4d-for-ios\/formatter-IntegerToImage\/collaborators{\/collaborator}","url":"https:\/\/api.github.com\/repos\/4d-for-ios\/formatter-IntegerToImage","default_branch":"master","archive_url":"https:\/\/api.github.com\/repos\/4d-for-ios\/formatter-IntegerToImage\/{archive_format}{\/ref}","forks_url":"https:\/\/api.github.com\/repos\/4d-for-ios\/formatter-IntegerToImage\/forks","fork":false,"release":{"tag_name":"0.0.1","upload_url":"https:\/\/uploads.github.com\/repos\/4d-for-ios\/formatter-IntegerToImage\/releases\/21737555\/assets{?name,label}","assets_url":"https:\/\/api.github.com\/repos\/4d-for-ios\/formatter-IntegerToImage\/releases\/21737555\/assets","created_at":"2019-11-25T09:45:21Z","prerelease":false,"author":{"gists_url":"https:\/\/api.github.com\/users\/phimage\/gists{\/gist_id}","type":"User","following_url":"https:\/\/api.github.com\/users\/phimage\/following{\/other_user}","followers_url":"https:\/\/api.github.com\/users\/phimage\/followers","gravatar_id":"","received_events_url":"https:\/\/api.github.com\/users\/phimage\/received_events","starred_url":"https:\/\/api.github.com\/users\/phimage\/starred{\/owner}{\/repo}","events_url":"https:\/\/api.github.com\/users\/phimage\/events{\/privacy}","organizations_url":"https:\/\/api.github.com\/users\/phimage\/orgs","avatar_url":"https:\/\/avatars.githubusercontent.com\/u\/8875768?v=4","repos_url":"https:\/\/api.github.com\/users\/phimage\/repos","html_url":"https:\/\/github.com\/phimage","site_admin":false,"url":"https:\/\/api.github.com\/users\/phimage","node_id":"MDQ6VXNlcjg4NzU3Njg=","login":"phimage","subscriptions_url":"https:\/\/api.github.com\/users\/phimage\/subscriptions","id":8875768},"published_at":"2019-11-25T15:43:26Z","draft":false,"id":21737555,"html_url":"https:\/\/github.com\/4d-for-ios\/formatter-IntegerToImage\/releases\/tag\/0.0.1","zipball_url":"https:\/\/api.github.com\/repos\/4d-for-ios\/formatter-IntegerToImage\/zipball\/0.0.1","name":null,"body":"🚀 Initial release","target_commitish":"master","assets":[{"state":"uploaded","label":"","created_at":"2019-11-25T15:56:14Z","content_type":"application\/zip","browser_download_url":"https:\/\/github.com\/4d-for-ios\/formatter-IntegerToImage\/releases\/download\/0.0.1\/formatter-IntegerToImage.zip","name":"formatter-IntegerToImage.zip","updated_at":"2019-11-25T15:56:14Z","url":"https:\/\/api.github.com\/repos\/4d-for-ios\/formatter-IntegerToImage\/releases\/assets\/16386909","uploader":{"gists_url":"https:\/\/api.github.com\/users\/github-actions%5Bbot%5D\/gists{\/gist_id}","html_url":"https:\/\/github.com\/apps\/github-actions","type":"Bot","id":41898282,"subscriptions_url":"https:\/\/api.github.com\/users\/github-actions%5Bbot%5D\/subscriptions","gravatar_id":"","following_url":"https:\/\/api.github.com\/users\/github-actions%5Bbot%5D\/following{\/other_user}","avatar_url":"https:\/\/avatars.githubusercontent.com\/in\/15368?v=4","node_id":"MDM6Qm90NDE4OTgyODI=","received_events_url":"https:\/\/api.github.com\/users\/github-actions%5Bbot%5D\/received_events","organizations_url":"https:\/\/api.github.com\/users\/github-actions%5Bbot%5D\/orgs","starred_url":"https:\/\/api.github.com\/users\/github-actions%5Bbot%5D\/starred{\/owner}{\/repo}","events_url":"https:\/\/api.github.com\/users\/github-actions%5Bbot%5D\/events{\/privacy}","repos_url":"https:\/\/api.github.com\/users\/github-actions%5Bbot%5D\/repos","followers_url":"https:\/\/api.github.com\/users\/github-actions%5Bbot%5D\/followers","site_admin":false,"login":"github-actions[bot]","url":"https:\/\/api.github.com\/users\/github-actions%5Bbot%5D"},"size":63700,"download_count":23,"node_id":"MDEyOlJlbGVhc2VBc3NldDE2Mzg2OTA5","id":16386909}],"node_id":"MDc6UmVsZWFzZTIxNzM3NTU1","url":"https:\/\/api.github.com\/repos\/4d-for-ios\/formatter-IntegerToImage\/releases\/21737555","tarball_url":"https:\/\/api.github.com\/repos\/4d-for-ios\/formatter-IntegerToImage\/tarball\/0.0.1"},"trees_url":"https:\/\/api.github.com\/repos\/4d-for-ios\/formatter-IntegerToImage\/git\/trees{\/sha}","branches_url":"https:\/\/api.github.com\/repos\/4d-for-ios\/formatter-IntegerToImage\/branches{\/branch}","notifications_url":"https:\/\/api.github.com\/repos\/4d-for-ios\/formatter-IntegerToImage\/notifications{?since,all,participating}","visibility":"public","temp_clone_token":"","deployments_url":"https:\/\/api.github.com\/repos\/4d-for-ios\/formatter-IntegerToImage\/deployments","tags_url":"https:\/\/api.github.com\/repos\/4d-for-ios\/formatter-IntegerToImage\/tags","ssh_url":"git@github.com:4d-for-ios\/formatter-IntegerToImage.git","stargazers_count":0,"assignees_url":"https:\/\/api.github.com\/repos\/4d-for-ios\/formatter-IntegerToImage\/assignees{\/user}","stargazers_url":"https:\/\/api.github.com\/repos\/4d-for-ios\/formatter-IntegerToImage\/stargazers","size":68,"has_issues":true,"issues_url":"https:\/\/api.github.com\/repos\/4d-for-ios\/formatter-IntegerToImage\/issues{\/number}","homepage":"https:\/\/developer.4d.com\/4d-for-ios\/docs\/en\/custom-data-formatters.html","milestones_url":"https:\/\/api.github.com\/repos\/4d-for-ios\/formatter-IntegerToImage\/milestones{\/number}","git_commits_url":"https:\/\/api.github.com\/repos\/4d-for-ios\/formatter-IntegerToImage\/git\/commits{\/sha}"}