{"organization":{"followers_url":"https:\/\/api.github.com\/users\/4d-for-mobile\/followers","url":"https:\/\/api.github.com\/users\/4d-for-mobile","events_url":"https:\/\/api.github.com\/users\/4d-for-mobile\/events{\/privacy}","site_admin":false,"avatar_url":"https:\/\/avatars.githubusercontent.com\/u\/79459282?v=4","id":79459282,"gists_url":"https:\/\/api.github.com\/users\/4d-for-mobile\/gists{\/gist_id}","gravatar_id":"","repos_url":"https:\/\/api.github.com\/users\/4d-for-mobile\/repos","node_id":"MDEyOk9yZ2FuaXphdGlvbjc5NDU5Mjgy","starred_url":"https:\/\/api.github.com\/users\/4d-for-mobile\/starred{\/owner}{\/repo}","html_url":"https:\/\/github.com\/4d-for-mobile","following_url":"https:\/\/api.github.com\/users\/4d-for-mobile\/following{\/other_user}","organizations_url":"https:\/\/api.github.com\/users\/4d-for-mobile\/orgs","received_events_url":"https:\/\/api.github.com\/users\/4d-for-mobile\/received_events","subscriptions_url":"https:\/\/api.github.com\/users\/4d-for-mobile\/subscriptions","login":"4d-for-mobile","type":"Organization"},"pushed_at":"2021-03-11T13:24:37Z","stargazers_count":0,"source":{"keys_url":"https:\/\/api.github.com\/repos\/4d-for-ios\/form-detail-Circle\/keys{\/key_id}","updated_at":"2020-09-24T13:56:56Z","tags_url":"https:\/\/api.github.com\/repos\/4d-for-ios\/form-detail-Circle\/tags","full_name":"4d-for-ios\/form-detail-Circle","visibility":"public","license":{"key":"other","node_id":"MDc6TGljZW5zZTA=","url":null,"spdx_id":"NOASSERTION","name":"Other"},"owner":{"followers_url":"https:\/\/api.github.com\/users\/4d-for-ios\/followers","url":"https:\/\/api.github.com\/users\/4d-for-ios","events_url":"https:\/\/api.github.com\/users\/4d-for-ios\/events{\/privacy}","site_admin":false,"avatar_url":"https:\/\/avatars.githubusercontent.com\/u\/57483781?v=4","id":57483781,"gists_url":"https:\/\/api.github.com\/users\/4d-for-ios\/gists{\/gist_id}","gravatar_id":"","repos_url":"https:\/\/api.github.com\/users\/4d-for-ios\/repos","node_id":"MDEyOk9yZ2FuaXphdGlvbjU3NDgzNzgx","starred_url":"https:\/\/api.github.com\/users\/4d-for-ios\/starred{\/owner}{\/repo}","html_url":"https:\/\/github.com\/4d-for-ios","following_url":"https:\/\/api.github.com\/users\/4d-for-ios\/following{\/other_user}","organizations_url":"https:\/\/api.github.com\/users\/4d-for-ios\/orgs","received_events_url":"https:\/\/api.github.com\/users\/4d-for-ios\/received_events","subscriptions_url":"https:\/\/api.github.com\/users\/4d-for-ios\/subscriptions","login":"4d-for-ios","type":"Organization"},"assignees_url":"https:\/\/api.github.com\/repos\/4d-for-ios\/form-detail-Circle\/assignees{\/user}","compare_url":"https:\/\/api.github.com\/repos\/4d-for-ios\/form-detail-Circle\/compare\/{base}...{head}","language":"Swift","default_branch":"master","has_downloads":true,"stargazers_url":"https:\/\/api.github.com\/repos\/4d-for-ios\/form-detail-Circle\/stargazers","name":"form-detail-Circle","branches_url":"https:\/\/api.github.com\/repos\/4d-for-ios\/form-detail-Circle\/branches{\/branch}","issues_url":"https:\/\/api.github.com\/repos\/4d-for-ios\/form-detail-Circle\/issues{\/number}","contributors_url":"https:\/\/api.github.com\/repos\/4d-for-ios\/form-detail-Circle\/contributors","merges_url":"https:\/\/api.github.com\/repos\/4d-for-ios\/form-detail-Circle\/merges","disabled":false,"contents_url":"https:\/\/api.github.com\/repos\/4d-for-ios\/form-detail-Circle\/contents\/{+path}","pushed_at":"2020-09-29T06:37:23Z","blobs_url":"https:\/\/api.github.com\/repos\/4d-for-ios\/form-detail-Circle\/git\/blobs{\/sha}","ssh_url":"git@github.com:4d-for-ios\/form-detail-Circle.git","description":"4D for iOS Detail Form template","issue_comment_url":"https:\/\/api.github.com\/repos\/4d-for-ios\/form-detail-Circle\/issues\/comments{\/number}","notifications_url":"https:\/\/api.github.com\/repos\/4d-for-ios\/form-detail-Circle\/notifications{?since,all,participating}","git_commits_url":"https:\/\/api.github.com\/repos\/4d-for-ios\/form-detail-Circle\/git\/commits{\/sha}","releases_url":"https:\/\/api.github.com\/repos\/4d-for-ios\/form-detail-Circle\/releases{\/id}","labels_url":"https:\/\/api.github.com\/repos\/4d-for-ios\/form-detail-Circle\/labels{\/name}","archived":false,"trees_url":"https:\/\/api.github.com\/repos\/4d-for-ios\/form-detail-Circle\/git\/trees{\/sha}","issue_events_url":"https:\/\/api.github.com\/repos\/4d-for-ios\/form-detail-Circle\/issues\/events{\/number}","open_issues":0,"html_url":"https:\/\/github.com\/4d-for-ios\/form-detail-Circle","milestones_url":"https:\/\/api.github.com\/repos\/4d-for-ios\/form-detail-Circle\/milestones{\/number}","stargazers_count":0,"fork":false,"pulls_url":"https:\/\/api.github.com\/repos\/4d-for-ios\/form-detail-Circle\/pulls{\/number}","svn_url":"https:\/\/github.com\/4d-for-ios\/form-detail-Circle","homepage":"","forks_url":"https:\/\/api.github.com\/repos\/4d-for-ios\/form-detail-Circle\/forks","subscription_url":"https:\/\/api.github.com\/repos\/4d-for-ios\/form-detail-Circle\/subscription","languages_url":"https:\/\/api.github.com\/repos\/4d-for-ios\/form-detail-Circle\/languages","open_issues_count":0,"has_issues":true,"git_url":"git:\/\/github.com\/4d-for-ios\/form-detail-Circle.git","subscribers_url":"https:\/\/api.github.com\/repos\/4d-for-ios\/form-detail-Circle\/subscribers","has_projects":true,"comments_url":"https:\/\/api.github.com\/repos\/4d-for-ios\/form-detail-Circle\/comments{\/number}","collaborators_url":"https:\/\/api.github.com\/repos\/4d-for-ios\/form-detail-Circle\/collaborators{\/collaborator}","created_at":"2019-11-04T07:27:30Z","url":"https:\/\/api.github.com\/repos\/4d-for-ios\/form-detail-Circle","watchers_count":0,"watchers":0,"deployments_url":"https:\/\/api.github.com\/repos\/4d-for-ios\/form-detail-Circle\/deployments","hooks_url":"https:\/\/api.github.com\/repos\/4d-for-ios\/form-detail-Circle\/hooks","git_refs_url":"https:\/\/api.github.com\/repos\/4d-for-ios\/form-detail-Circle\/git\/refs{\/sha}","size":530,"mirror_url":null,"clone_url":"https:\/\/github.com\/4d-for-ios\/form-detail-Circle.git","events_url":"https:\/\/api.github.com\/repos\/4d-for-ios\/form-detail-Circle\/events","statuses_url":"https:\/\/api.github.com\/repos\/4d-for-ios\/form-detail-Circle\/statuses\/{sha}","forks":1,"forks_count":1,"teams_url":"https:\/\/api.github.com\/repos\/4d-for-ios\/form-detail-Circle\/teams","commits_url":"https:\/\/api.github.com\/repos\/4d-for-ios\/form-detail-Circle\/commits{\/sha}","downloads_url":"https:\/\/api.github.com\/repos\/4d-for-ios\/form-detail-Circle\/downloads","id":219441846,"has_wiki":true,"git_tags_url":"https:\/\/api.github.com\/repos\/4d-for-ios\/form-detail-Circle\/git\/tags{\/sha}","archive_url":"https:\/\/api.github.com\/repos\/4d-for-ios\/form-detail-Circle\/{archive_format}{\/ref}","node_id":"MDEwOlJlcG9zaXRvcnkyMTk0NDE4NDY=","has_pages":false,"private":false},"assignees_url":"https:\/\/api.github.com\/repos\/4d-for-mobile\/form-detail-Circle\/assignees{\/user}","pulls_url":"https:\/\/api.github.com\/repos\/4d-for-mobile\/form-detail-Circle\/pulls{\/number}","forks_url":"https:\/\/api.github.com\/repos\/4d-for-mobile\/form-detail-Circle\/forks","merges_url":"https:\/\/api.github.com\/repos\/4d-for-mobile\/form-detail-Circle\/merges","archive_url":"https:\/\/api.github.com\/repos\/4d-for-mobile\/form-detail-Circle\/{archive_format}{\/ref}","git_url":"git:\/\/github.com\/4d-for-mobile\/form-detail-Circle.git","created_at":"2021-03-09T21:17:23Z","private":false,"statuses_url":"https:\/\/api.github.com\/repos\/4d-for-mobile\/form-detail-Circle\/statuses\/{sha}","watchers_count":0,"keys_url":"https:\/\/api.github.com\/repos\/4d-for-mobile\/form-detail-Circle\/keys{\/key_id}","release":{"assets":[{"uploader":{"site_admin":false,"type":"Bot","followers_url":"https:\/\/api.github.com\/users\/github-actions%5Bbot%5D\/followers","gravatar_id":"","repos_url":"https:\/\/api.github.com\/users\/github-actions%5Bbot%5D\/repos","login":"github-actions[bot]","events_url":"https:\/\/api.github.com\/users\/github-actions%5Bbot%5D\/events{\/privacy}","organizations_url":"https:\/\/api.github.com\/users\/github-actions%5Bbot%5D\/orgs","starred_url":"https:\/\/api.github.com\/users\/github-actions%5Bbot%5D\/starred{\/owner}{\/repo}","subscriptions_url":"https:\/\/api.github.com\/users\/github-actions%5Bbot%5D\/subscriptions","url":"https:\/\/api.github.com\/users\/github-actions%5Bbot%5D","id":41898282,"node_id":"MDM6Qm90NDE4OTgyODI=","html_url":"https:\/\/github.com\/apps\/github-actions","received_events_url":"https:\/\/api.github.com\/users\/github-actions%5Bbot%5D\/received_events","gists_url":"https:\/\/api.github.com\/users\/github-actions%5Bbot%5D\/gists{\/gist_id}","following_url":"https:\/\/api.github.com\/users\/github-actions%5Bbot%5D\/following{\/other_user}","avatar_url":"https:\/\/avatars.githubusercontent.com\/in\/15368?v=4"},"url":"https:\/\/api.github.com\/repos\/4d-for-mobile\/form-detail-Circle\/releases\/assets\/33333671","node_id":"MDEyOlJlbGVhc2VBc3NldDMzMzMzNjcx","browser_download_url":"https:\/\/github.com\/4d-for-mobile\/form-detail-Circle\/releases\/download\/0.1.0\/form-detail-Circle.zip","updated_at":"2021-03-11T17:44:34Z","id":33333671,"created_at":"2021-03-11T17:44:33Z","content_type":"application\/zip","state":"uploaded","download_count":1,"label":"","size":526608,"name":"form-detail-Circle.zip"}],"html_url":"https:\/\/github.com\/4d-for-mobile\/form-detail-Circle\/releases\/tag\/0.1.0","created_at":"2021-03-11T13:20:33Z","upload_url":"https:\/\/uploads.github.com\/repos\/4d-for-mobile\/form-detail-Circle\/releases\/39653920\/assets{?name,label}","id":39653920,"tarball_url":"https:\/\/api.github.com\/repos\/4d-for-mobile\/form-detail-Circle\/tarball\/0.1.0","draft":false,"url":"https:\/\/api.github.com\/repos\/4d-for-mobile\/form-detail-Circle\/releases\/39653920","node_id":"MDc6UmVsZWFzZTM5NjUzOTIw","zipball_url":"https:\/\/api.github.com\/repos\/4d-for-mobile\/form-detail-Circle\/zipball\/0.1.0","target_commitish":"master","assets_url":"https:\/\/api.github.com\/repos\/4d-for-mobile\/form-detail-Circle\/releases\/39653920\/assets","name":null,"body":"🤖 android first release","published_at":"2021-03-11T13:24:37Z","tag_name":"0.1.0","prerelease":false,"author":{"following_url":"https:\/\/api.github.com\/users\/mesopelagique\/following{\/other_user}","received_events_url":"https:\/\/api.github.com\/users\/mesopelagique\/received_events","avatar_url":"https:\/\/avatars.githubusercontent.com\/u\/59135882?v=4","followers_url":"https:\/\/api.github.com\/users\/mesopelagique\/followers","subscriptions_url":"https:\/\/api.github.com\/users\/mesopelagique\/subscriptions","starred_url":"https:\/\/api.github.com\/users\/mesopelagique\/starred{\/owner}{\/repo}","login":"mesopelagique","gravatar_id":"","events_url":"https:\/\/api.github.com\/users\/mesopelagique\/events{\/privacy}","html_url":"https:\/\/github.com\/mesopelagique","type":"User","gists_url":"https:\/\/api.github.com\/users\/mesopelagique\/gists{\/gist_id}","site_admin":false,"node_id":"MDQ6VXNlcjU5MTM1ODgy","url":"https:\/\/api.github.com\/users\/mesopelagique","repos_url":"https:\/\/api.github.com\/users\/mesopelagique\/repos","organizations_url":"https:\/\/api.github.com\/users\/mesopelagique\/orgs","id":59135882}},"permissions":{"push":false,"pull":false,"admin":false},"archived":false,"license":{"node_id":"MDc6TGljZW5zZTA=","name":"Other","spdx_id":"NOASSERTION","key":"other","url":null},"has_pages":false,"name":"form-detail-Circle","owner":{"followers_url":"https:\/\/api.github.com\/users\/4d-for-mobile\/followers","url":"https:\/\/api.github.com\/users\/4d-for-mobile","events_url":"https:\/\/api.github.com\/users\/4d-for-mobile\/events{\/privacy}","site_admin":false,"avatar_url":"https:\/\/avatars.githubusercontent.com\/u\/79459282?v=4","id":79459282,"gists_url":"https:\/\/api.github.com\/users\/4d-for-mobile\/gists{\/gist_id}","gravatar_id":"","repos_url":"https:\/\/api.github.com\/users\/4d-for-mobile\/repos","node_id":"MDEyOk9yZ2FuaXphdGlvbjc5NDU5Mjgy","starred_url":"https:\/\/api.github.com\/users\/4d-for-mobile\/starred{\/owner}{\/repo}","html_url":"https:\/\/github.com\/4d-for-mobile","following_url":"https:\/\/api.github.com\/users\/4d-for-mobile\/following{\/other_user}","organizations_url":"https:\/\/api.github.com\/users\/4d-for-mobile\/orgs","received_events_url":"https:\/\/api.github.com\/users\/4d-for-mobile\/received_events","subscriptions_url":"https:\/\/api.github.com\/users\/4d-for-mobile\/subscriptions","login":"4d-for-mobile","type":"Organization"},"disabled":false,"updated_at":"2021-03-11T13:20:37Z","teams_url":"https:\/\/api.github.com\/repos\/4d-for-mobile\/form-detail-Circle\/teams","milestones_url":"https:\/\/api.github.com\/repos\/4d-for-mobile\/form-detail-Circle\/milestones{\/number}","size":532,"description":"4D for iOS Detail Form template","contents_url":"https:\/\/api.github.com\/repos\/4d-for-mobile\/form-detail-Circle\/contents\/{+path}","releases_url":"https:\/\/api.github.com\/repos\/4d-for-mobile\/form-detail-Circle\/releases{\/id}","commits_url":"https:\/\/api.github.com\/repos\/4d-for-mobile\/form-detail-Circle\/commits{\/sha}","subscribers_url":"https:\/\/api.github.com\/repos\/4d-for-mobile\/form-detail-Circle\/subscribers","forks_count":0,"downloads_url":"https:\/\/api.github.com\/repos\/4d-for-mobile\/form-detail-Circle\/downloads","has_issues":false,"issue_events_url":"https:\/\/api.github.com\/repos\/4d-for-mobile\/form-detail-Circle\/issues\/events{\/number}","visibility":"public","full_name":"4d-for-mobile\/form-detail-Circle","git_tags_url":"https:\/\/api.github.com\/repos\/4d-for-mobile\/form-detail-Circle\/git\/tags{\/sha}","git_refs_url":"https:\/\/api.github.com\/repos\/4d-for-mobile\/form-detail-Circle\/git\/refs{\/sha}","issue_comment_url":"https:\/\/api.github.com\/repos\/4d-for-mobile\/form-detail-Circle\/issues\/comments{\/number}","tags_url":"https:\/\/api.github.com\/repos\/4d-for-mobile\/form-detail-Circle\/tags","watchers":0,"mirror_url":null,"languages_url":"https:\/\/api.github.com\/repos\/4d-for-mobile\/form-detail-Circle\/languages","has_wiki":true,"open_issues":0,"git_commits_url":"https:\/\/api.github.com\/repos\/4d-for-mobile\/form-detail-Circle\/git\/commits{\/sha}","collaborators_url":"https:\/\/api.github.com\/repos\/4d-for-mobile\/form-detail-Circle\/collaborators{\/collaborator}","notifications_url":"https:\/\/api.github.com\/repos\/4d-for-mobile\/form-detail-Circle\/notifications{?since,all,participating}","hooks_url":"https:\/\/api.github.com\/repos\/4d-for-mobile\/form-detail-Circle\/hooks","language":"Swift","contributors_url":"https:\/\/api.github.com\/repos\/4d-for-mobile\/form-detail-Circle\/contributors","has_downloads":true,"stargazers_url":"https:\/\/api.github.com\/repos\/4d-for-mobile\/form-detail-Circle\/stargazers","default_branch":"master","id":346146883,"compare_url":"https:\/\/api.github.com\/repos\/4d-for-mobile\/form-detail-Circle\/compare\/{base}...{head}","has_projects":true,"blobs_url":"https:\/\/api.github.com\/repos\/4d-for-mobile\/form-detail-Circle\/git\/blobs{\/sha}","trees_url":"https:\/\/api.github.com\/repos\/4d-for-mobile\/form-detail-Circle\/git\/trees{\/sha}","labels_url":"https:\/\/api.github.com\/repos\/4d-for-mobile\/form-detail-Circle\/labels{\/name}","homepage":"","fork":true,"url":"https:\/\/api.github.com\/repos\/4d-for-mobile\/form-detail-Circle","deployments_url":"https:\/\/api.github.com\/repos\/4d-for-mobile\/form-detail-Circle\/deployments","parent":{"keys_url":"https:\/\/api.github.com\/repos\/4d-for-ios\/form-detail-Circle\/keys{\/key_id}","updated_at":"2020-09-24T13:56:56Z","tags_url":"https:\/\/api.github.com\/repos\/4d-for-ios\/form-detail-Circle\/tags","full_name":"4d-for-ios\/form-detail-Circle","visibility":"public","license":{"node_id":"MDc6TGljZW5zZTA=","name":"Other","spdx_id":"NOASSERTION","key":"other","url":null},"owner":{"followers_url":"https:\/\/api.github.com\/users\/4d-for-ios\/followers","url":"https:\/\/api.github.com\/users\/4d-for-ios","events_url":"https:\/\/api.github.com\/users\/4d-for-ios\/events{\/privacy}","site_admin":false,"avatar_url":"https:\/\/avatars.githubusercontent.com\/u\/57483781?v=4","id":57483781,"gists_url":"https:\/\/api.github.com\/users\/4d-for-ios\/gists{\/gist_id}","gravatar_id":"","repos_url":"https:\/\/api.github.com\/users\/4d-for-ios\/repos","node_id":"MDEyOk9yZ2FuaXphdGlvbjU3NDgzNzgx","starred_url":"https:\/\/api.github.com\/users\/4d-for-ios\/starred{\/owner}{\/repo}","html_url":"https:\/\/github.com\/4d-for-ios","following_url":"https:\/\/api.github.com\/users\/4d-for-ios\/following{\/other_user}","organizations_url":"https:\/\/api.github.com\/users\/4d-for-ios\/orgs","received_events_url":"https:\/\/api.github.com\/users\/4d-for-ios\/received_events","subscriptions_url":"https:\/\/api.github.com\/users\/4d-for-ios\/subscriptions","login":"4d-for-ios","type":"Organization"},"assignees_url":"https:\/\/api.github.com\/repos\/4d-for-ios\/form-detail-Circle\/assignees{\/user}","compare_url":"https:\/\/api.github.com\/repos\/4d-for-ios\/form-detail-Circle\/compare\/{base}...{head}","language":"Swift","default_branch":"master","has_downloads":true,"stargazers_url":"https:\/\/api.github.com\/repos\/4d-for-ios\/form-detail-Circle\/stargazers","name":"form-detail-Circle","branches_url":"https:\/\/api.github.com\/repos\/4d-for-ios\/form-detail-Circle\/branches{\/branch}","issues_url":"https:\/\/api.github.com\/repos\/4d-for-ios\/form-detail-Circle\/issues{\/number}","contributors_url":"https:\/\/api.github.com\/repos\/4d-for-ios\/form-detail-Circle\/contributors","merges_url":"https:\/\/api.github.com\/repos\/4d-for-ios\/form-detail-Circle\/merges","disabled":false,"contents_url":"https:\/\/api.github.com\/repos\/4d-for-ios\/form-detail-Circle\/contents\/{+path}","pushed_at":"2020-09-29T06:37:23Z","blobs_url":"https:\/\/api.github.com\/repos\/4d-for-ios\/form-detail-Circle\/git\/blobs{\/sha}","ssh_url":"git@github.com:4d-for-ios\/form-detail-Circle.git","description":"4D for iOS Detail Form template","issue_comment_url":"https:\/\/api.github.com\/repos\/4d-for-ios\/form-detail-Circle\/issues\/comments{\/number}","notifications_url":"https:\/\/api.github.com\/repos\/4d-for-ios\/form-detail-Circle\/notifications{?since,all,participating}","git_commits_url":"https:\/\/api.github.com\/repos\/4d-for-ios\/form-detail-Circle\/git\/commits{\/sha}","releases_url":"https:\/\/api.github.com\/repos\/4d-for-ios\/form-detail-Circle\/releases{\/id}","labels_url":"https:\/\/api.github.com\/repos\/4d-for-ios\/form-detail-Circle\/labels{\/name}","archived":false,"trees_url":"https:\/\/api.github.com\/repos\/4d-for-ios\/form-detail-Circle\/git\/trees{\/sha}","issue_events_url":"https:\/\/api.github.com\/repos\/4d-for-ios\/form-detail-Circle\/issues\/events{\/number}","open_issues":0,"html_url":"https:\/\/github.com\/4d-for-ios\/form-detail-Circle","milestones_url":"https:\/\/api.github.com\/repos\/4d-for-ios\/form-detail-Circle\/milestones{\/number}","stargazers_count":0,"fork":false,"pulls_url":"https:\/\/api.github.com\/repos\/4d-for-ios\/form-detail-Circle\/pulls{\/number}","svn_url":"https:\/\/github.com\/4d-for-ios\/form-detail-Circle","homepage":"","forks_url":"https:\/\/api.github.com\/repos\/4d-for-ios\/form-detail-Circle\/forks","subscription_url":"https:\/\/api.github.com\/repos\/4d-for-ios\/form-detail-Circle\/subscription","languages_url":"https:\/\/api.github.com\/repos\/4d-for-ios\/form-detail-Circle\/languages","open_issues_count":0,"has_issues":true,"git_url":"git:\/\/github.com\/4d-for-ios\/form-detail-Circle.git","subscribers_url":"https:\/\/api.github.com\/repos\/4d-for-ios\/form-detail-Circle\/subscribers","has_projects":true,"comments_url":"https:\/\/api.github.com\/repos\/4d-for-ios\/form-detail-Circle\/comments{\/number}","collaborators_url":"https:\/\/api.github.com\/repos\/4d-for-ios\/form-detail-Circle\/collaborators{\/collaborator}","created_at":"2019-11-04T07:27:30Z","url":"https:\/\/api.github.com\/repos\/4d-for-ios\/form-detail-Circle","watchers_count":0,"watchers":0,"deployments_url":"https:\/\/api.github.com\/repos\/4d-for-ios\/form-detail-Circle\/deployments","hooks_url":"https:\/\/api.github.com\/repos\/4d-for-ios\/form-detail-Circle\/hooks","git_refs_url":"https:\/\/api.github.com\/repos\/4d-for-ios\/form-detail-Circle\/git\/refs{\/sha}","size":530,"mirror_url":null,"clone_url":"https:\/\/github.com\/4d-for-ios\/form-detail-Circle.git","events_url":"https:\/\/api.github.com\/repos\/4d-for-ios\/form-detail-Circle\/events","statuses_url":"https:\/\/api.github.com\/repos\/4d-for-ios\/form-detail-Circle\/statuses\/{sha}","forks":1,"forks_count":1,"teams_url":"https:\/\/api.github.com\/repos\/4d-for-ios\/form-detail-Circle\/teams","commits_url":"https:\/\/api.github.com\/repos\/4d-for-ios\/form-detail-Circle\/commits{\/sha}","downloads_url":"https:\/\/api.github.com\/repos\/4d-for-ios\/form-detail-Circle\/downloads","id":219441846,"has_wiki":true,"git_tags_url":"https:\/\/api.github.com\/repos\/4d-for-ios\/form-detail-Circle\/git\/tags{\/sha}","archive_url":"https:\/\/api.github.com\/repos\/4d-for-ios\/form-detail-Circle\/{archive_format}{\/ref}","node_id":"MDEwOlJlcG9zaXRvcnkyMTk0NDE4NDY=","has_pages":false,"private":false},"svn_url":"https:\/\/github.com\/4d-for-mobile\/form-detail-Circle","temp_clone_token":"","html_url":"https:\/\/github.com\/4d-for-mobile\/form-detail-Circle","subscription_url":"https:\/\/api.github.com\/repos\/4d-for-mobile\/form-detail-Circle\/subscription","events_url":"https:\/\/api.github.com\/repos\/4d-for-mobile\/form-detail-Circle\/events","open_issues_count":0,"comments_url":"https:\/\/api.github.com\/repos\/4d-for-mobile\/form-detail-Circle\/comments{\/number}","clone_url":"https:\/\/github.com\/4d-for-mobile\/form-detail-Circle.git","forks":0,"issues_url":"https:\/\/api.github.com\/repos\/4d-for-mobile\/form-detail-Circle\/issues{\/number}","branches_url":"https:\/\/api.github.com\/repos\/4d-for-mobile\/form-detail-Circle\/branches{\/branch}","ssh_url":"git@github.com:4d-for-mobile\/form-detail-Circle.git","network_count":1,"node_id":"MDEwOlJlcG9zaXRvcnkzNDYxNDY4ODM=","subscribers_count":0}