{"subscribers_count":0,"branches_url":"https:\/\/api.github.com\/repos\/4d-for-mobile\/form-list-TasksCollection\/branches{\/branch}","issues_url":"https:\/\/api.github.com\/repos\/4d-for-mobile\/form-list-TasksCollection\/issues{\/number}","visibility":"public","source":{"git_commits_url":"https:\/\/api.github.com\/repos\/4d-for-ios\/form-list-TasksCollection\/git\/commits{\/sha}","issue_comment_url":"https:\/\/api.github.com\/repos\/4d-for-ios\/form-list-TasksCollection\/issues\/comments{\/number}","fork":false,"license":{"name":"Other","key":"other","url":null,"node_id":"MDc6TGljZW5zZTA=","spdx_id":"NOASSERTION"},"url":"https:\/\/api.github.com\/repos\/4d-for-ios\/form-list-TasksCollection","has_wiki":true,"labels_url":"https:\/\/api.github.com\/repos\/4d-for-ios\/form-list-TasksCollection\/labels{\/name}","has_issues":true,"merges_url":"https:\/\/api.github.com\/repos\/4d-for-ios\/form-list-TasksCollection\/merges","subscription_url":"https:\/\/api.github.com\/repos\/4d-for-ios\/form-list-TasksCollection\/subscription","branches_url":"https:\/\/api.github.com\/repos\/4d-for-ios\/form-list-TasksCollection\/branches{\/branch}","mirror_url":null,"svn_url":"https:\/\/github.com\/4d-for-ios\/form-list-TasksCollection","releases_url":"https:\/\/api.github.com\/repos\/4d-for-ios\/form-list-TasksCollection\/releases{\/id}","events_url":"https:\/\/api.github.com\/repos\/4d-for-ios\/form-list-TasksCollection\/events","trees_url":"https:\/\/api.github.com\/repos\/4d-for-ios\/form-list-TasksCollection\/git\/trees{\/sha}","compare_url":"https:\/\/api.github.com\/repos\/4d-for-ios\/form-list-TasksCollection\/compare\/{base}...{head}","git_refs_url":"https:\/\/api.github.com\/repos\/4d-for-ios\/form-list-TasksCollection\/git\/refs{\/sha}","git_url":"git:\/\/github.com\/4d-for-ios\/form-list-TasksCollection.git","commits_url":"https:\/\/api.github.com\/repos\/4d-for-ios\/form-list-TasksCollection\/commits{\/sha}","open_issues":0,"teams_url":"https:\/\/api.github.com\/repos\/4d-for-ios\/form-list-TasksCollection\/teams","comments_url":"https:\/\/api.github.com\/repos\/4d-for-ios\/form-list-TasksCollection\/comments{\/number}","forks":1,"downloads_url":"https:\/\/api.github.com\/repos\/4d-for-ios\/form-list-TasksCollection\/downloads","pulls_url":"https:\/\/api.github.com\/repos\/4d-for-ios\/form-list-TasksCollection\/pulls{\/number}","private":false,"forks_url":"https:\/\/api.github.com\/repos\/4d-for-ios\/form-list-TasksCollection\/forks","archived":false,"archive_url":"https:\/\/api.github.com\/repos\/4d-for-ios\/form-list-TasksCollection\/{archive_format}{\/ref}","issues_url":"https:\/\/api.github.com\/repos\/4d-for-ios\/form-list-TasksCollection\/issues{\/number}","created_at":"2019-06-05T09:33:59Z","keys_url":"https:\/\/api.github.com\/repos\/4d-for-ios\/form-list-TasksCollection\/keys{\/key_id}","name":"form-list-TasksCollection","contributors_url":"https:\/\/api.github.com\/repos\/4d-for-ios\/form-list-TasksCollection\/contributors","watchers":0,"updated_at":"2020-03-30T07:18:38Z","ssh_url":"git@github.com:4d-for-ios\/form-list-TasksCollection.git","has_downloads":true,"hooks_url":"https:\/\/api.github.com\/repos\/4d-for-ios\/form-list-TasksCollection\/hooks","size":1715,"id":190367082,"full_name":"4d-for-ios\/form-list-TasksCollection","forks_count":1,"description":"4D for iOS List Form template","open_issues_count":0,"owner":{"login":"4d-for-ios","starred_url":"https:\/\/api.github.com\/users\/4d-for-ios\/starred{\/owner}{\/repo}","gists_url":"https:\/\/api.github.com\/users\/4d-for-ios\/gists{\/gist_id}","type":"Organization","id":57483781,"site_admin":false,"avatar_url":"https:\/\/avatars.githubusercontent.com\/u\/57483781?v=4","node_id":"MDEyOk9yZ2FuaXphdGlvbjU3NDgzNzgx","repos_url":"https:\/\/api.github.com\/users\/4d-for-ios\/repos","url":"https:\/\/api.github.com\/users\/4d-for-ios","following_url":"https:\/\/api.github.com\/users\/4d-for-ios\/following{\/other_user}","events_url":"https:\/\/api.github.com\/users\/4d-for-ios\/events{\/privacy}","subscriptions_url":"https:\/\/api.github.com\/users\/4d-for-ios\/subscriptions","received_events_url":"https:\/\/api.github.com\/users\/4d-for-ios\/received_events","gravatar_id":"","html_url":"https:\/\/github.com\/4d-for-ios","organizations_url":"https:\/\/api.github.com\/users\/4d-for-ios\/orgs","followers_url":"https:\/\/api.github.com\/users\/4d-for-ios\/followers"},"tags_url":"https:\/\/api.github.com\/repos\/4d-for-ios\/form-list-TasksCollection\/tags","disabled":false,"blobs_url":"https:\/\/api.github.com\/repos\/4d-for-ios\/form-list-TasksCollection\/git\/blobs{\/sha}","issue_events_url":"https:\/\/api.github.com\/repos\/4d-for-ios\/form-list-TasksCollection\/issues\/events{\/number}","statuses_url":"https:\/\/api.github.com\/repos\/4d-for-ios\/form-list-TasksCollection\/statuses\/{sha}","language":"Swift","default_branch":"master","subscribers_url":"https:\/\/api.github.com\/repos\/4d-for-ios\/form-list-TasksCollection\/subscribers","deployments_url":"https:\/\/api.github.com\/repos\/4d-for-ios\/form-list-TasksCollection\/deployments","languages_url":"https:\/\/api.github.com\/repos\/4d-for-ios\/form-list-TasksCollection\/languages","git_tags_url":"https:\/\/api.github.com\/repos\/4d-for-ios\/form-list-TasksCollection\/git\/tags{\/sha}","has_projects":false,"node_id":"MDEwOlJlcG9zaXRvcnkxOTAzNjcwODI=","stargazers_count":0,"collaborators_url":"https:\/\/api.github.com\/repos\/4d-for-ios\/form-list-TasksCollection\/collaborators{\/collaborator}","html_url":"https:\/\/github.com\/4d-for-ios\/form-list-TasksCollection","watchers_count":0,"visibility":"public","homepage":"https:\/\/developer.4d.com\/4d-for-ios\/docs\/en\/custom-listform-templates.html","notifications_url":"https:\/\/api.github.com\/repos\/4d-for-ios\/form-list-TasksCollection\/notifications{?since,all,participating}","has_pages":false,"stargazers_url":"https:\/\/api.github.com\/repos\/4d-for-ios\/form-list-TasksCollection\/stargazers","contents_url":"https:\/\/api.github.com\/repos\/4d-for-ios\/form-list-TasksCollection\/contents\/{+path}","milestones_url":"https:\/\/api.github.com\/repos\/4d-for-ios\/form-list-TasksCollection\/milestones{\/number}","pushed_at":"2020-03-30T07:20:42Z","clone_url":"https:\/\/github.com\/4d-for-ios\/form-list-TasksCollection.git","assignees_url":"https:\/\/api.github.com\/repos\/4d-for-ios\/form-list-TasksCollection\/assignees{\/user}"},"archived":false,"language":"Swift","stargazers_count":0,"has_projects":true,"id":346146582,"permissions":{"admin":false,"pull":false,"push":false},"pulls_url":"https:\/\/api.github.com\/repos\/4d-for-mobile\/form-list-TasksCollection\/pulls{\/number}","svn_url":"https:\/\/github.com\/4d-for-mobile\/form-list-TasksCollection","watchers_count":0,"deployments_url":"https:\/\/api.github.com\/repos\/4d-for-mobile\/form-list-TasksCollection\/deployments","fork":true,"blobs_url":"https:\/\/api.github.com\/repos\/4d-for-mobile\/form-list-TasksCollection\/git\/blobs{\/sha}","git_refs_url":"https:\/\/api.github.com\/repos\/4d-for-mobile\/form-list-TasksCollection\/git\/refs{\/sha}","releases_url":"https:\/\/api.github.com\/repos\/4d-for-mobile\/form-list-TasksCollection\/releases{\/id}","node_id":"MDEwOlJlcG9zaXRvcnkzNDYxNDY1ODI=","milestones_url":"https:\/\/api.github.com\/repos\/4d-for-mobile\/form-list-TasksCollection\/milestones{\/number}","ssh_url":"git@github.com:4d-for-mobile\/form-list-TasksCollection.git","created_at":"2021-03-09T21:16:17Z","labels_url":"https:\/\/api.github.com\/repos\/4d-for-mobile\/form-list-TasksCollection\/labels{\/name}","git_commits_url":"https:\/\/api.github.com\/repos\/4d-for-mobile\/form-list-TasksCollection\/git\/commits{\/sha}","description":"4D for iOS List Form template","has_pages":false,"downloads_url":"https:\/\/api.github.com\/repos\/4d-for-mobile\/form-list-TasksCollection\/downloads","compare_url":"https:\/\/api.github.com\/repos\/4d-for-mobile\/form-list-TasksCollection\/compare\/{base}...{head}","clone_url":"https:\/\/github.com\/4d-for-mobile\/form-list-TasksCollection.git","trees_url":"https:\/\/api.github.com\/repos\/4d-for-mobile\/form-list-TasksCollection\/git\/trees{\/sha}","assignees_url":"https:\/\/api.github.com\/repos\/4d-for-mobile\/form-list-TasksCollection\/assignees{\/user}","watchers":0,"html_url":"https:\/\/github.com\/4d-for-mobile\/form-list-TasksCollection","has_wiki":true,"statuses_url":"https:\/\/api.github.com\/repos\/4d-for-mobile\/form-list-TasksCollection\/statuses\/{sha}","release":{"published_at":"2021-03-11T12:49:12Z","upload_url":"https:\/\/uploads.github.com\/repos\/4d-for-mobile\/form-list-TasksCollection\/releases\/39651894\/assets{?name,label}","html_url":"https:\/\/github.com\/4d-for-mobile\/form-list-TasksCollection\/releases\/tag\/0.1.0","node_id":"MDc6UmVsZWFzZTM5NjUxODk0","zipball_url":"https:\/\/api.github.com\/repos\/4d-for-mobile\/form-list-TasksCollection\/zipball\/0.1.0","created_at":"2021-03-11T10:24:01Z","author":{"url":"https:\/\/api.github.com\/users\/mesopelagique","following_url":"https:\/\/api.github.com\/users\/mesopelagique\/following{\/other_user}","repos_url":"https:\/\/api.github.com\/users\/mesopelagique\/repos","type":"User","gists_url":"https:\/\/api.github.com\/users\/mesopelagique\/gists{\/gist_id}","starred_url":"https:\/\/api.github.com\/users\/mesopelagique\/starred{\/owner}{\/repo}","site_admin":false,"organizations_url":"https:\/\/api.github.com\/users\/mesopelagique\/orgs","subscriptions_url":"https:\/\/api.github.com\/users\/mesopelagique\/subscriptions","received_events_url":"https:\/\/api.github.com\/users\/mesopelagique\/received_events","html_url":"https:\/\/github.com\/mesopelagique","avatar_url":"https:\/\/avatars.githubusercontent.com\/u\/59135882?v=4","followers_url":"https:\/\/api.github.com\/users\/mesopelagique\/followers","login":"mesopelagique","events_url":"https:\/\/api.github.com\/users\/mesopelagique\/events{\/privacy}","id":59135882,"node_id":"MDQ6VXNlcjU5MTM1ODgy","gravatar_id":""},"draft":false,"assets_url":"https:\/\/api.github.com\/repos\/4d-for-mobile\/form-list-TasksCollection\/releases\/39651894\/assets","name":null,"body":"🤖 android first release","tarball_url":"https:\/\/api.github.com\/repos\/4d-for-mobile\/form-list-TasksCollection\/tarball\/0.1.0","target_commitish":"master","assets":[{"url":"https:\/\/api.github.com\/repos\/4d-for-mobile\/form-list-TasksCollection\/releases\/assets\/33327282","uploader":{"html_url":"https:\/\/github.com\/apps\/github-actions","repos_url":"https:\/\/api.github.com\/users\/github-actions%5Bbot%5D\/repos","id":41898282,"gravatar_id":"","type":"Bot","login":"github-actions[bot]","gists_url":"https:\/\/api.github.com\/users\/github-actions%5Bbot%5D\/gists{\/gist_id}","node_id":"MDM6Qm90NDE4OTgyODI=","following_url":"https:\/\/api.github.com\/users\/github-actions%5Bbot%5D\/following{\/other_user}","url":"https:\/\/api.github.com\/users\/github-actions%5Bbot%5D","starred_url":"https:\/\/api.github.com\/users\/github-actions%5Bbot%5D\/starred{\/owner}{\/repo}","followers_url":"https:\/\/api.github.com\/users\/github-actions%5Bbot%5D\/followers","site_admin":false,"events_url":"https:\/\/api.github.com\/users\/github-actions%5Bbot%5D\/events{\/privacy}","avatar_url":"https:\/\/avatars.githubusercontent.com\/in\/15368?v=4","received_events_url":"https:\/\/api.github.com\/users\/github-actions%5Bbot%5D\/received_events","organizations_url":"https:\/\/api.github.com\/users\/github-actions%5Bbot%5D\/orgs","subscriptions_url":"https:\/\/api.github.com\/users\/github-actions%5Bbot%5D\/subscriptions"},"updated_at":"2021-03-11T15:26:14Z","name":"form-list-TasksCollection.zip","browser_download_url":"https:\/\/github.com\/4d-for-mobile\/form-list-TasksCollection\/releases\/download\/0.1.0\/form-list-TasksCollection.zip","content_type":"application\/zip","label":"","download_count":1,"size":1725293,"node_id":"MDEyOlJlbGVhc2VBc3NldDMzMzI3Mjgy","id":33327282,"created_at":"2021-03-11T15:26:12Z","state":"uploaded"}],"tag_name":"0.1.0","url":"https:\/\/api.github.com\/repos\/4d-for-mobile\/form-list-TasksCollection\/releases\/39651894","prerelease":false,"id":39651894},"forks":0,"full_name":"4d-for-mobile\/form-list-TasksCollection","updated_at":"2021-03-11T10:24:06Z","archive_url":"https:\/\/api.github.com\/repos\/4d-for-mobile\/form-list-TasksCollection\/{archive_format}{\/ref}","git_url":"git:\/\/github.com\/4d-for-mobile\/form-list-TasksCollection.git","disabled":false,"private":false,"hooks_url":"https:\/\/api.github.com\/repos\/4d-for-mobile\/form-list-TasksCollection\/hooks","git_tags_url":"https:\/\/api.github.com\/repos\/4d-for-mobile\/form-list-TasksCollection\/git\/tags{\/sha}","forks_url":"https:\/\/api.github.com\/repos\/4d-for-mobile\/form-list-TasksCollection\/forks","issue_comment_url":"https:\/\/api.github.com\/repos\/4d-for-mobile\/form-list-TasksCollection\/issues\/comments{\/number}","contents_url":"https:\/\/api.github.com\/repos\/4d-for-mobile\/form-list-TasksCollection\/contents\/{+path}","network_count":1,"notifications_url":"https:\/\/api.github.com\/repos\/4d-for-mobile\/form-list-TasksCollection\/notifications{?since,all,participating}","open_issues_count":0,"name":"form-list-TasksCollection","subscription_url":"https:\/\/api.github.com\/repos\/4d-for-mobile\/form-list-TasksCollection\/subscription","organization":{"login":"4d-for-mobile","starred_url":"https:\/\/api.github.com\/users\/4d-for-mobile\/starred{\/owner}{\/repo}","gists_url":"https:\/\/api.github.com\/users\/4d-for-mobile\/gists{\/gist_id}","type":"Organization","id":79459282,"site_admin":false,"avatar_url":"https:\/\/avatars.githubusercontent.com\/u\/79459282?v=4","node_id":"MDEyOk9yZ2FuaXphdGlvbjc5NDU5Mjgy","repos_url":"https:\/\/api.github.com\/users\/4d-for-mobile\/repos","url":"https:\/\/api.github.com\/users\/4d-for-mobile","following_url":"https:\/\/api.github.com\/users\/4d-for-mobile\/following{\/other_user}","events_url":"https:\/\/api.github.com\/users\/4d-for-mobile\/events{\/privacy}","subscriptions_url":"https:\/\/api.github.com\/users\/4d-for-mobile\/subscriptions","received_events_url":"https:\/\/api.github.com\/users\/4d-for-mobile\/received_events","gravatar_id":"","html_url":"https:\/\/github.com\/4d-for-mobile","organizations_url":"https:\/\/api.github.com\/users\/4d-for-mobile\/orgs","followers_url":"https:\/\/api.github.com\/users\/4d-for-mobile\/followers"},"events_url":"https:\/\/api.github.com\/repos\/4d-for-mobile\/form-list-TasksCollection\/events","pushed_at":"2021-03-11T12:49:12Z","default_branch":"master","forks_count":0,"license":{"name":"Other","key":"other","url":null,"node_id":"MDc6TGljZW5zZTA=","spdx_id":"NOASSERTION"},"homepage":"https:\/\/developer.4d.com\/4d-for-ios\/docs\/en\/custom-listform-templates.html","issue_events_url":"https:\/\/api.github.com\/repos\/4d-for-mobile\/form-list-TasksCollection\/issues\/events{\/number}","stargazers_url":"https:\/\/api.github.com\/repos\/4d-for-mobile\/form-list-TasksCollection\/stargazers","subscribers_url":"https:\/\/api.github.com\/repos\/4d-for-mobile\/form-list-TasksCollection\/subscribers","has_downloads":true,"temp_clone_token":"","url":"https:\/\/api.github.com\/repos\/4d-for-mobile\/form-list-TasksCollection","merges_url":"https:\/\/api.github.com\/repos\/4d-for-mobile\/form-list-TasksCollection\/merges","comments_url":"https:\/\/api.github.com\/repos\/4d-for-mobile\/form-list-TasksCollection\/comments{\/number}","keys_url":"https:\/\/api.github.com\/repos\/4d-for-mobile\/form-list-TasksCollection\/keys{\/key_id}","size":1700,"contributors_url":"https:\/\/api.github.com\/repos\/4d-for-mobile\/form-list-TasksCollection\/contributors","mirror_url":null,"parent":{"git_commits_url":"https:\/\/api.github.com\/repos\/4d-for-ios\/form-list-TasksCollection\/git\/commits{\/sha}","issue_comment_url":"https:\/\/api.github.com\/repos\/4d-for-ios\/form-list-TasksCollection\/issues\/comments{\/number}","fork":false,"license":{"name":"Other","key":"other","url":null,"node_id":"MDc6TGljZW5zZTA=","spdx_id":"NOASSERTION"},"url":"https:\/\/api.github.com\/repos\/4d-for-ios\/form-list-TasksCollection","has_wiki":true,"labels_url":"https:\/\/api.github.com\/repos\/4d-for-ios\/form-list-TasksCollection\/labels{\/name}","has_issues":true,"merges_url":"https:\/\/api.github.com\/repos\/4d-for-ios\/form-list-TasksCollection\/merges","subscription_url":"https:\/\/api.github.com\/repos\/4d-for-ios\/form-list-TasksCollection\/subscription","branches_url":"https:\/\/api.github.com\/repos\/4d-for-ios\/form-list-TasksCollection\/branches{\/branch}","mirror_url":null,"svn_url":"https:\/\/github.com\/4d-for-ios\/form-list-TasksCollection","releases_url":"https:\/\/api.github.com\/repos\/4d-for-ios\/form-list-TasksCollection\/releases{\/id}","events_url":"https:\/\/api.github.com\/repos\/4d-for-ios\/form-list-TasksCollection\/events","trees_url":"https:\/\/api.github.com\/repos\/4d-for-ios\/form-list-TasksCollection\/git\/trees{\/sha}","compare_url":"https:\/\/api.github.com\/repos\/4d-for-ios\/form-list-TasksCollection\/compare\/{base}...{head}","git_refs_url":"https:\/\/api.github.com\/repos\/4d-for-ios\/form-list-TasksCollection\/git\/refs{\/sha}","git_url":"git:\/\/github.com\/4d-for-ios\/form-list-TasksCollection.git","commits_url":"https:\/\/api.github.com\/repos\/4d-for-ios\/form-list-TasksCollection\/commits{\/sha}","open_issues":0,"teams_url":"https:\/\/api.github.com\/repos\/4d-for-ios\/form-list-TasksCollection\/teams","comments_url":"https:\/\/api.github.com\/repos\/4d-for-ios\/form-list-TasksCollection\/comments{\/number}","forks":1,"downloads_url":"https:\/\/api.github.com\/repos\/4d-for-ios\/form-list-TasksCollection\/downloads","pulls_url":"https:\/\/api.github.com\/repos\/4d-for-ios\/form-list-TasksCollection\/pulls{\/number}","private":false,"forks_url":"https:\/\/api.github.com\/repos\/4d-for-ios\/form-list-TasksCollection\/forks","archived":false,"archive_url":"https:\/\/api.github.com\/repos\/4d-for-ios\/form-list-TasksCollection\/{archive_format}{\/ref}","issues_url":"https:\/\/api.github.com\/repos\/4d-for-ios\/form-list-TasksCollection\/issues{\/number}","created_at":"2019-06-05T09:33:59Z","keys_url":"https:\/\/api.github.com\/repos\/4d-for-ios\/form-list-TasksCollection\/keys{\/key_id}","name":"form-list-TasksCollection","contributors_url":"https:\/\/api.github.com\/repos\/4d-for-ios\/form-list-TasksCollection\/contributors","watchers":0,"updated_at":"2020-03-30T07:18:38Z","ssh_url":"git@github.com:4d-for-ios\/form-list-TasksCollection.git","has_downloads":true,"hooks_url":"https:\/\/api.github.com\/repos\/4d-for-ios\/form-list-TasksCollection\/hooks","size":1715,"id":190367082,"full_name":"4d-for-ios\/form-list-TasksCollection","forks_count":1,"description":"4D for iOS List Form template","open_issues_count":0,"owner":{"login":"4d-for-ios","starred_url":"https:\/\/api.github.com\/users\/4d-for-ios\/starred{\/owner}{\/repo}","gists_url":"https:\/\/api.github.com\/users\/4d-for-ios\/gists{\/gist_id}","type":"Organization","id":57483781,"site_admin":false,"avatar_url":"https:\/\/avatars.githubusercontent.com\/u\/57483781?v=4","node_id":"MDEyOk9yZ2FuaXphdGlvbjU3NDgzNzgx","repos_url":"https:\/\/api.github.com\/users\/4d-for-ios\/repos","url":"https:\/\/api.github.com\/users\/4d-for-ios","following_url":"https:\/\/api.github.com\/users\/4d-for-ios\/following{\/other_user}","events_url":"https:\/\/api.github.com\/users\/4d-for-ios\/events{\/privacy}","subscriptions_url":"https:\/\/api.github.com\/users\/4d-for-ios\/subscriptions","received_events_url":"https:\/\/api.github.com\/users\/4d-for-ios\/received_events","gravatar_id":"","html_url":"https:\/\/github.com\/4d-for-ios","organizations_url":"https:\/\/api.github.com\/users\/4d-for-ios\/orgs","followers_url":"https:\/\/api.github.com\/users\/4d-for-ios\/followers"},"tags_url":"https:\/\/api.github.com\/repos\/4d-for-ios\/form-list-TasksCollection\/tags","disabled":false,"blobs_url":"https:\/\/api.github.com\/repos\/4d-for-ios\/form-list-TasksCollection\/git\/blobs{\/sha}","issue_events_url":"https:\/\/api.github.com\/repos\/4d-for-ios\/form-list-TasksCollection\/issues\/events{\/number}","statuses_url":"https:\/\/api.github.com\/repos\/4d-for-ios\/form-list-TasksCollection\/statuses\/{sha}","language":"Swift","default_branch":"master","subscribers_url":"https:\/\/api.github.com\/repos\/4d-for-ios\/form-list-TasksCollection\/subscribers","deployments_url":"https:\/\/api.github.com\/repos\/4d-for-ios\/form-list-TasksCollection\/deployments","languages_url":"https:\/\/api.github.com\/repos\/4d-for-ios\/form-list-TasksCollection\/languages","git_tags_url":"https:\/\/api.github.com\/repos\/4d-for-ios\/form-list-TasksCollection\/git\/tags{\/sha}","has_projects":false,"node_id":"MDEwOlJlcG9zaXRvcnkxOTAzNjcwODI=","stargazers_count":0,"collaborators_url":"https:\/\/api.github.com\/repos\/4d-for-ios\/form-list-TasksCollection\/collaborators{\/collaborator}","html_url":"https:\/\/github.com\/4d-for-ios\/form-list-TasksCollection","watchers_count":0,"visibility":"public","homepage":"https:\/\/developer.4d.com\/4d-for-ios\/docs\/en\/custom-listform-templates.html","notifications_url":"https:\/\/api.github.com\/repos\/4d-for-ios\/form-list-TasksCollection\/notifications{?since,all,participating}","has_pages":false,"stargazers_url":"https:\/\/api.github.com\/repos\/4d-for-ios\/form-list-TasksCollection\/stargazers","contents_url":"https:\/\/api.github.com\/repos\/4d-for-ios\/form-list-TasksCollection\/contents\/{+path}","milestones_url":"https:\/\/api.github.com\/repos\/4d-for-ios\/form-list-TasksCollection\/milestones{\/number}","pushed_at":"2020-03-30T07:20:42Z","clone_url":"https:\/\/github.com\/4d-for-ios\/form-list-TasksCollection.git","assignees_url":"https:\/\/api.github.com\/repos\/4d-for-ios\/form-list-TasksCollection\/assignees{\/user}"},"languages_url":"https:\/\/api.github.com\/repos\/4d-for-mobile\/form-list-TasksCollection\/languages","collaborators_url":"https:\/\/api.github.com\/repos\/4d-for-mobile\/form-list-TasksCollection\/collaborators{\/collaborator}","owner":{"login":"4d-for-mobile","starred_url":"https:\/\/api.github.com\/users\/4d-for-mobile\/starred{\/owner}{\/repo}","gists_url":"https:\/\/api.github.com\/users\/4d-for-mobile\/gists{\/gist_id}","type":"Organization","id":79459282,"site_admin":false,"avatar_url":"https:\/\/avatars.githubusercontent.com\/u\/79459282?v=4","node_id":"MDEyOk9yZ2FuaXphdGlvbjc5NDU5Mjgy","repos_url":"https:\/\/api.github.com\/users\/4d-for-mobile\/repos","url":"https:\/\/api.github.com\/users\/4d-for-mobile","following_url":"https:\/\/api.github.com\/users\/4d-for-mobile\/following{\/other_user}","events_url":"https:\/\/api.github.com\/users\/4d-for-mobile\/events{\/privacy}","subscriptions_url":"https:\/\/api.github.com\/users\/4d-for-mobile\/subscriptions","received_events_url":"https:\/\/api.github.com\/users\/4d-for-mobile\/received_events","gravatar_id":"","html_url":"https:\/\/github.com\/4d-for-mobile","organizations_url":"https:\/\/api.github.com\/users\/4d-for-mobile\/orgs","followers_url":"https:\/\/api.github.com\/users\/4d-for-mobile\/followers"},"commits_url":"https:\/\/api.github.com\/repos\/4d-for-mobile\/form-list-TasksCollection\/commits{\/sha}","open_issues":0,"teams_url":"https:\/\/api.github.com\/repos\/4d-for-mobile\/form-list-TasksCollection\/teams","has_issues":false,"tags_url":"https:\/\/api.github.com\/repos\/4d-for-mobile\/form-list-TasksCollection\/tags"}